README.txt
bootstrap.py
buildout.cfg
setup.cfg
setup.py
collective/__init__.py
collective.recipe.libsvm.egg-info/PKG-INFO
collective.recipe.libsvm.egg-info/SOURCES.txt
collective.recipe.libsvm.egg-info/dependency_links.txt
collective.recipe.libsvm.egg-info/entry_points.txt
collective.recipe.libsvm.egg-info/namespace_packages.txt
collective.recipe.libsvm.egg-info/not-zip-safe
collective.recipe.libsvm.egg-info/requires.txt
collective.recipe.libsvm.egg-info/top_level.txt
collective/recipe/__init__.py
collective/recipe/libsvm/README.txt
collective/recipe/libsvm/__init__.py
collective/recipe/libsvm/recipe.py
collective/recipe/libsvm/tests/__init__.py
collective/recipe/libsvm/tests/test_docs.py
docs/HISTORY.txt