Metadata-Version: 1.0
Name: collective.recipe.libsvm
Version: 0.1
Summary: Recipe to compile libsvm with python in a buildout
Home-page: http://svn.plone.org/svn/collective/collective.recipe.libsvm
Author: Jean-Francois Roche
Author-email: jfroche@affinitic.be
License: GPL
Platform: UNKNOWN
Classifier: Programming Language :: Python
Classifier: Topic :: Software Development :: Libraries :: Python Modules
Classifier: License :: OSI Approved :: GNU General Public License (GPL)
Classifier: Programming Language :: Python
Classifier: Topic :: System :: Installation/Setup
Classifier: Topic :: Software Development :: Libraries :: Python Modules
Classifier: Framework :: Buildout
